matrixchain/__init__.py
matrixchain/__main__.py
matrixchain/core.py
matrixchain-1.0.1.dist-info/licenses/LICENSE
matrixchain-1.0.1.dist-info/METADATA
matrixchain-1.0.1.dist-info/WHEEL
matrixchain-1.0.1.dist-info/entry_points.txt
matrixchain-1.0.1.dist-info/top_level.txt
matrixchain-1.0.1.dist-info/RECORD
