Metadata-Version: 2.4
Name: matrixchain
Version: 1.0.1
Summary: Hacker-style Matrix Chain Multiplication visualizer
Author: Chauhan Pruthviraj
Author-email: Chauhan Pruthviraj <chauhanpruthviraj309@gmail.com>
License-Expression: MIT
Project-URL: Homepage, https://github.com/Pruthviraj36/matrixchain
Project-URL: Bug Reports, https://github.com/Pruthviraj36/matrixchain/issues
Project-URL: Source Code, https://github.com/Pruthviraj36/matrixchain
Keywords: matrix,multiplication,dynamic-programming,algorithm,visualization,education
Classifier: Development Status :: 5 - Production/Stable
Classifier: Intended Audience :: Education
Classifier: Intended Audience :: Developers
Classifier: Operating System :: OS Independent
Classifier: Programming Language :: Python :: 3
Classifier: Programming Language :: Python :: 3.7
Classifier: Programming Language :: Python :: 3.8
Classifier: Programming Language :: Python :: 3.9
Classifier: Programming Language :: Python :: 3.10
Classifier: Programming Language :: Python :: 3.11
Classifier: Topic :: Education
Classifier: Topic :: Scientific/Engineering :: Mathematics
Classifier: Topic :: Software Development :: Libraries :: Python Modules
Requires-Python: >=3.7
License-File: LICENSE
Requires-Dist: colorama>=0.4.0
Dynamic: author
Dynamic: license-file
Dynamic: requires-python
